CFaqLite/README.md
CFaqLite/__init__.py
CFaqLite/__main__.py
CFaqLite/file.epub
CFaqLite/index.html
CFaqLite/css/__init__.py
CFaqLite/css/annotations.css
CFaqLite/css/main.css
CFaqLite/css/normalize.css
CFaqLite/css/popup.css
CFaqLite/font/__init__.py
CFaqLite/font/fontello.eot
CFaqLite/font/fontello.svg
CFaqLite/font/fontello.ttf
CFaqLite/font/fontello.woff
CFaqLite/img/__init__.py
CFaqLite/img/annotator-glyph-sprite.png
CFaqLite/img/annotator-icon-sprite.png
CFaqLite/img/apple-touch-icon.png
CFaqLite/img/cancelfullscreen.png
CFaqLite/img/close.png
CFaqLite/img/fullscreen.png
CFaqLite/img/loader.gif
CFaqLite/img/menu-icon.png
CFaqLite/img/save.png
CFaqLite/img/saved.png
CFaqLite/img/settings-s.png
CFaqLite/img/settings.png
CFaqLite/img/star.png
CFaqLite/js/__init__.py
CFaqLite/js/epub.js
CFaqLite/js/epub.min.js
CFaqLite/js/epub.min.map
CFaqLite/js/hooks.min.js
CFaqLite/js/hooks.min.map
CFaqLite/js/reader.js
CFaqLite/js/reader.js.map
CFaqLite/js/reader.min.js
CFaqLite/js/reader.min.map
CFaqLite/js/hooks/__init__.py
CFaqLite/js/hooks/extensions/__init__.py
CFaqLite/js/hooks/extensions/highlight.js
CFaqLite/js/libs/__init__.py
CFaqLite/js/libs/jquery.min.js
CFaqLite/js/libs/localforage.min.js
CFaqLite/js/libs/screenfull.js
CFaqLite/js/libs/screenfull.min.js
CFaqLite/js/libs/zip.min.js
CFaqLite/js/plugins/__init__.py
CFaqLite/js/plugins/hypothesis.js
CFaqLite/js/plugins/search.js
c_faq_lite-2024.3.1.0.dist-info/METADATA
c_faq_lite-2024.3.1.0.dist-info/WHEEL
c_faq_lite-2024.3.1.0.dist-info/entry_points.txt
c_faq_lite-2024.3.1.0.dist-info/top_level.txt
c_faq_lite-2024.3.1.0.dist-info/RECORD
